verilog/test_clock_big_vcd.v
// EXPECT=PASS
`timescale 1ns/1ps

module tb;
  reg clk;
  reg rst;
  reg enable;
  reg [7:0] counter;
  reg [7:0] accum;
  reg [3:0] lfsr;
  reg [15:0] shreg;

  wire [7:0] mix = counter + {4'b0, lfsr};
  wire pulse = (counter[5:0] == 6'h3f);

  initial begin
    $dumpfile("test_clock_big_vcd.vcd");
    $dumpvars(0, tb);
  end

  initial begin
    clk = 1'b0;
    rst = 1'b1;
    enable = 1'b0;
    counter = 8'h00;
    accum = 8'h00;
    lfsr = 4'h1;
    shreg = 16'h0001;

    #25 rst = 1'b0;
    repeat (400) @(posedge clk);
    $finish;
  end

  always #5 clk = ~clk;

  always @(posedge clk) begin
    if (rst) begin
      counter <= 8'h00;
      accum <= 8'h00;
      lfsr <= 4'h1;
      shreg <= 16'h0001;
      enable <= 1'b0;
    end else begin
      counter <= counter + 8'h01;
      lfsr <= {lfsr[2:0], lfsr[3] ^ lfsr[2]};
      shreg <= {shreg[14:0], shreg[15] ^ shreg[13]};
      if (counter[2:0] == 3'b111) begin
        enable <= ~enable;
      end
      if (enable) begin
        accum <= accum + mix;
      end else if (pulse) begin
        accum <= accum ^ mix;
      end else begin
        accum <= accum - 8'h01;
      end
    end
  end
endmodule

goldVDCs/test_clock_big_4state.vcd
$date
  today
$end
$version
  metalfpga
$end
$timescale 1ns $end
$scope module tb $end
$var wire 8 " accum $end
$var wire 1 # clk $end
$var wire 8 & counter $end
$var wire 1 ) enable $end
$var wire 4 ( lfsr $end
$var wire 8 ! mix $end
$var wire 1 ' pulse $end
$var wire 1 $ rst $end
$var wire 16 % shreg $end
$upscope $end
$enddefinitions $end
#0
bzzzzzzzz !
bxxxxxxxx "
x#
x$
bxxxxxxxxxxxxxxxx %
bxxxxxxxx &
z'
bxxxx (
x)
0#
1$
0)
b00000000 &
b00000000 "
0'
b0001 (
b00000001 !
b0000000000000001 %
#5
bzzzzzzzz !
bxxxxxxxx "
1#
bxxxxxxxxxxxxxxxx %
bxxxxxxxx &
z'
bxxxx (
x)
#10
b00000001 !
b00000000 "
0#
b0000000000000001 %
b00000000 &
0'
b0001 (
0)
#15
1#
#20
0#
#25
0$
1#
#30
b00000011 !
b11111111 "
0#
b0000000000000010 %
b00000001 &
b0010 (
#35
1#
#40
b00000110 !
b11111110 "
0#
b0000000000000100 %
b00000010 &
b0100 (
#45
1#
#50
b00001100 !
b11111101 "
0#
b0000000000001000 %
b00000011 &
b1001 (
#55
1#
#60
b00000111 !
b11111100 "
0#
b0000000000010000 %
b00000100 &
b0011 (
#65
1#
#70
b00001011 !
b11111011 "
0#
b0000000000100000 %
b00000101 &
b0110 (
#75
1#
#80
b00010011 !
b11111010 "
0#
b0000000001000000 %
b00000110 &
b1101 (
#85
1#
#90
b00010001 !
b11111001 "
0#
b0000000010000000 %
b00000111 &
b1010 (
#95
1#
#100
b00001101 !
b11111000 "
0#
b0000000100000000 %
b00001000 &
b0101 (
1)
#105
1#
#110
b00010100 !
b00000101 "
0#
b0000001000000000 %
b00001001 &
b1011 (
#115
1#
#120
b00010001 !
b00011001 "
0#
b0000010000000000 %
b00001010 &
b0111 (
#125
1#
#130
b00011010 !
b00101010 "
0#
b0000100000000000 %
b00001011 &
b1111 (
#135
1#
#140
b01000100 "
0#
b0001000000000000 %
b00001100 &
b1110 (
#145
1#
#150
b00011001 !
b01011110 "
0#
b0010000000000000 %
b00001101 &
b1100 (
#155
1#
#160
b00010110 !
b01110111 "
0#
b0100000000000001 %
b00001110 &
b1000 (
#165
1#
#170
b00010000 !
b10001101 "
0#
b1000000000000010 %
b00001111 &
b0001 (
#175
1#
#180
b00010010 !
b10011101 "
0#
b0000000000000101 %
b00010000 &
b0010 (
0)
#185
1#
#190
b00010101 !
b10011100 "
0#
b0000000000001010 %
b00010001 &
b0100 (
#195
1#
#200
b00011011 !
b10011011 "
0#
b0000000000010100 %
b00010010 &
b1001 (
#205
1#
#210
b00010110 !
b10011010 "
0#
b0000000000101000 %
b00010011 &
b0011 (
#215
1#
#220
b00011010 !
b10011001 "
0#
b0000000001010000 %
b00010100 &
b0110 (
#225
1#
#230
b00100010 !
b10011000 "
0#
b0000000010100000 %
b00010101 &
b1101 (
#235
1#
#240
b00100000 !
b10010111 "
0#
b0000000101000000 %
b00010110 &
b1010 (
#245
1#
#250
b00011100 !
b10010110 "
0#
b0000001010000000 %
b00010111 &
b0101 (
#255
1#
#260
b00100011 !
b10010101 "
0#
b0000010100000000 %
b00011000 &
b1011 (
1)
#265
1#
#270
b00100000 !
b10111000 "
0#
b0000101000000000 %
b00011001 &
b0111 (
#275
1#
#280
b00101001 !
b11011000 "
0#
b0001010000000000 %
b00011010 &
b1111 (
#285
1#
#290
b00000001 "
0#
b0010100000000000 %
b00011011 &
b1110 (
#295
1#
#300
b00101000 !
b00101010 "
0#
b0101000000000001 %
b00011100 &
b1100 (
#305
1#
#310
b00100101 !
b01010010 "
0#
b1010000000000010 %
b00011101 &
b1000 (
#315
1#
#320
b00011111 !
b01110111 "
0#
b0100000000000100 %
b00011110 &
b0001 (
#325
1#
#330
b00100001 !
b10010110 "
0#
b1000000000001000 %
b00011111 &
b0010 (
#335
1#
#340
b00100100 !
b10110111 "
0#
b0000000000010001 %
b00100000 &
b0100 (
0)
#345
1#
#350
b00101010 !
b10110110 "
0#
b0000000000100010 %
b00100001 &
b1001 (
#355
1#
#360
b00100101 !
b10110101 "
0#
b0000000001000100 %
b00100010 &
b0011 (
#365
1#
#370
b00101001 !
b10110100 "
0#
b0000000010001000 %
b00100011 &
b0110 (
#375
1#
#380
b00110001 !
b10110011 "
0#
b0000000100010000 %
b00100100 &
b1101 (
#385
1#
#390
b00101111 !
b10110010 "
0#
b0000001000100000 %
b00100101 &
b1010 (
#395
1#
#400
b00101011 !
b10110001 "
0#
b0000010001000000 %
b00100110 &
b0101 (
#405
1#
#410
b00110010 !
b10110000 "
0#
b0000100010000000 %
b00100111 &
b1011 (
#415
1#
#420
b00101111 !
b10101111 "
0#
b0001000100000000 %
b00101000 &
b0111 (
1)
#425
1#
#430
b00111000 !
b11011110 "
0#
b0010001000000000 %
b00101001 &
b1111 (
#435
1#
#440
b00010110 "
0#
b0100010000000001 %
b00101010 &
b1110 (
#445
1#
#450
b00110111 !
b01001110 "
0#
b1000100000000010 %
b00101011 &
b1100 (
#455
1#
#460
b00110100 !
b10000101 "
0#
b0001000000000101 %
b00101100 &
b1000 (
#465
1#
#470
b00101110 !
b10111001 "
0#
b0010000000001010 %
b00101101 &
b0001 (
#475
1#
#480
b00110000 !
b11100111 "
0#
b0100000000010101 %
b00101110 &
b0010 (
#485
1#
#490
b00110011 !
b00010111 "
0#
b1000000000101010 %
b00101111 &
b0100 (
#495
1#
#500
b00111001 !
b01001010 "
0#
b0000000001010101 %
b00110000 &
b1001 (
0)
#505
1#
#510
b00110100 !
b01001001 "
0#
b0000000010101010 %
b00110001 &
b0011 (
#515
1#
#520
b00111000 !
b01001000 "
0#
b0000000101010100 %
b00110010 &
b0110 (
#525
1#
#530
b01000000 !
b01000111 "
0#
b0000001010101000 %
b00110011 &
b1101 (
#535
1#
#540
b00111110 !
b01000110 "
0#
b0000010101010000 %
b00110100 &
b1010 (
#545
1#
#550
b00111010 !
b01000101 "
0#
b0000101010100000 %
b00110101 &
b0101 (
#555
1#
#560
b01000001 !
b01000100 "
0#
b0001010101000000 %
b00110110 &
b1011 (
#565
1#
#570
b00111110 !
b01000011 "
0#
b0010101010000000 %
b00110111 &
b0111 (
#575
1#
#580
b01000111 !
b01000010 "
0#
b0101010100000001 %
b00111000 &
b1111 (
1)
#585
1#
#590
b10001001 "
0#
b1010101000000010 %
b00111001 &
b1110 (
#595
1#
#600
b01000110 !
b11010000 "
0#
b0101010000000100 %
b00111010 &
b1100 (
#605
1#
#610
b01000011 !
b00010110 "
0#
b1010100000001000 %
b00111011 &
b1000 (
#615
1#
#620
b00111101 !
b01011001 "
0#
b0101000000010000 %
b00111100 &
b0001 (
#625
1#
#630
b00111111 !
b10010110 "
0#
b1010000000100000 %
b00111101 &
b0010 (
#635
1#
#640
b01000010 !
b11010101 "
0#
b0100000001000000 %
b00111110 &
b0100 (
#645
1#
#650
b01001000 !
b00010111 "
0#
b1000000010000000 %
b00111111 &
1'
b1001 (
#655
1#
#660
b01000011 !
b01011111 "
0#
b0000000100000001 %
b01000000 &
0'
b0011 (
0)
#665
1#
#670
b01000111 !
b01011110 "
0#
b0000001000000010 %
b01000001 &
b0110 (
#675
1#
#680
b01001111 !
b01011101 "
0#
b0000010000000100 %
b01000010 &
b1101 (
#685
1#
#690
b01001101 !
b01011100 "
0#
b0000100000001000 %
b01000011 &
b1010 (
#695
1#
#700
b01001001 !
b01011011 "
0#
b0001000000010000 %
b01000100 &
b0101 (
#705
1#
#710
b01010000 !
b01011010 "
0#
b0010000000100000 %
b01000101 &
b1011 (
#715
1#
#720
b01001101 !
b01011001 "
0#
b0100000001000001 %
b01000110 &
b0111 (
#725
1#
#730
b01010110 !
b01011000 "
0#
b1000000010000010 %
b01000111 &
b1111 (
#735
1#
#740
b01010111 "
0#
b0000000100000101 %
b01001000 &
b1110 (
1)
#745
1#
#750
b01010101 !
b10101101 "
0#
b0000001000001010 %
b01001001 &
b1100 (
#755
1#
#760
b01010010 !
b00000010 "
0#
b0000010000010100 %
b01001010 &
b1000 (
#765
1#
#770
b01001100 !
b01010100 "
0#
b0000100000101000 %
b01001011 &
b0001 (
#775
1#
#780
b01001110 !
b10100000 "
0#
b0001000001010000 %
b01001100 &
b0010 (
#785
1#
#790
b01010001 !
b11101110 "
0#
b0010000010100000 %
b01001101 &
b0100 (
#795
1#
#800
b01010111 !
b00111111 "
0#
b0100000101000001 %
b01001110 &
b1001 (
#805
1#
#810
b01010010 !
b10010110 "
0#
b1000001010000010 %
b01001111 &
b0011 (
#815
1#
#820
b01010110 !
b11101000 "
0#
b0000010100000101 %
b01010000 &
b0110 (
0)
#825
1#
#830
b01011110 !
b11100111 "
0#
b0000101000001010 %
b01010001 &
b1101 (
#835
1#
#840
b01011100 !
b11100110 "
0#
b0001010000010100 %
b01010010 &
b1010 (
#845
1#
#850
b01011000 !
b11100101 "
0#
b0010100000101000 %
b01010011 &
b0101 (
#855
1#
#860
b01011111 !
b11100100 "
0#
b0101000001010001 %
b01010100 &
b1011 (
#865
1#
#870
b01011100 !
b11100011 "
0#
b1010000010100010 %
b01010101 &
b0111 (
#875
1#
#880
b01100101 !
b11100010 "
0#
b0100000101000100 %
b01010110 &
b1111 (
#885
1#
#890
b11100001 "
0#
b1000001010001000 %
b01010111 &
b1110 (
#895
1#
#900
b01100100 !
b11100000 "
0#
b0000010100010001 %
b01011000 &
b1100 (
1)
#905
1#
#910
b01100001 !
b01000100 "
0#
b0000101000100010 %
b01011001 &
b1000 (
#915
1#
#920
b01011011 !
b10100101 "
0#
b0001010001000100 %
b01011010 &
b0001 (
#925
1#
#930
b01011101 !
b00000000 "
0#
b0010100010001000 %
b01011011 &
b0010 (
#935
1#
#940
b01100000 !
b01011101 "
0#
b0101000100010001 %
b01011100 &
b0100 (
#945
1#
#950
b01100110 !
b10111101 "
0#
b1010001000100010 %
b01011101 &
b1001 (
#955
1#
#960
b01100001 !
b00100011 "
0#
b0100010001000100 %
b01011110 &
b0011 (
#965
1#
#970
b01100101 !
b10000100 "
0#
b1000100010001000 %
b01011111 &
b0110 (
#975
1#
#980
b01101101 !
b11101001 "
0#
b0001000100010001 %
b01100000 &
b1101 (
0)
#985
1#
#990
b01101011 !
b11101000 "
0#
b0010001000100010 %
b01100001 &
b1010 (
#995
1#
#1000
b01100111 !
b11100111 "
0#
b0100010001000101 %
b01100010 &
b0101 (
#1005
1#
#1010
b01101110 !
b11100110 "
0#
b1000100010001010 %
b01100011 &
b1011 (
#1015
1#
#1020
b01101011 !
b11100101 "
0#
b0001000100010101 %
b01100100 &
b0111 (
#1025
1#
#1030
b01110100 !
b11100100 "
0#
b0010001000101010 %
b01100101 &
b1111 (
#1035
1#
#1040
b11100011 "
0#
b0100010001010101 %
b01100110 &
b1110 (
#1045
1#
#1050
b01110011 !
b11100010 "
0#
b1000100010101010 %
b01100111 &
b1100 (
#1055
1#
#1060
b01110000 !
b11100001 "
0#
b0001000101010101 %
b01101000 &
b1000 (
1)
#1065
1#
#1070
b01101010 !
b01010001 "
0#
b0010001010101010 %
b01101001 &
b0001 (
#1075
1#
#1080
b01101100 !
b10111011 "
0#
b0100010101010101 %
b01101010 &
b0010 (
#1085
1#
#1090
b01101111 !
b00100111 "
0#
b1000101010101010 %
b01101011 &
b0100 (
#1095
1#
#1100
b01110101 !
b10010110 "
0#
b0001010101010101 %
b01101100 &
b1001 (
#1105
1#
#1110
b01110000 !
b00001011 "
0#
b0010101010101010 %
b01101101 &
b0011 (
#1115
1#
#1120
b01110100 !
b01111011 "
0#
b0101010101010101 %
b01101110 &
b0110 (
#1125
1#
#1130
b01111100 !
b11101111 "
0#
b1010101010101010 %
b01101111 &
b1101 (
#1135
1#
#1140
b01111010 !
b01101011 "
0#
b0101010101010100 %
b01110000 &
b1010 (
0)
#1145
1#
#1150
b01110110 !
b01101010 "
0#
b1010101010101000 %
b01110001 &
b0101 (
#1155
1#
#1160
b01111101 !
b01101001 "
0#
b0101010101010000 %
b01110010 &
b1011 (
#1165
1#
#1170
b01111010 !
b01101000 "
0#
b1010101010100000 %
b01110011 &
b0111 (
#1175
1#
#1180
b10000011 !
b01100111 "
0#
b0101010101000000 %
b01110100 &
b1111 (
#1185
1#
#1190
b01100110 "
0#
b1010101010000000 %
b01110101 &
b1110 (
#1195
1#
#1200
b10000010 !
b01100101 "
0#
b0101010100000000 %
b01110110 &
b1100 (
#1205
1#
#1210
b01111111 !
b01100100 "
0#
b1010101000000000 %
b01110111 &
b1000 (
#1215
1#
#1220
b01111001 !
b01100011 "
0#
b0101010000000000 %
b01111000 &
b0001 (
1)
#1225
1#
#1230
b01111011 !
b11011100 "
0#
b1010100000000000 %
b01111001 &
b0010 (
#1235
1#
#1240
b01111110 !
b01010111 "
0#
b0101000000000000 %
b01111010 &
b0100 (
#1245
1#
#1250
b10000100 !
b11010101 "
0#
b1010000000000000 %
b01111011 &
b1001 (
#1255
1#
#1260
b01111111 !
b01011001 "
0#
b0100000000000000 %
b01111100 &
b0011 (
#1265
1#
#1270
b10000011 !
b11011000 "
0#
b1000000000000000 %
b01111101 &
b0110 (
#1275
1#
#1280
b10001011 !
b01011011 "
0#
b0000000000000001 %
b01111110 &
b1101 (
#1285
1#
#1290
b10001001 !
b11100110 "
0#
b0000000000000010 %
b01111111 &
1'
b1010 (
#1295
1#
#1300
b10000101 !
b01101111 "
0#
b0000000000000100 %
b10000000 &
0'
b0101 (
0)
#1305
1#
#1310
b10001100 !
b01101110 "
0#
b0000000000001000 %
b10000001 &
b1011 (
#1315
1#
#1320
b10001001 !
b01101101 "
0#
b0000000000010000 %
b10000010 &
b0111 (
#1325
1#
#1330
b10010010 !
b01101100 "
0#
b0000000000100000 %
b10000011 &
b1111 (
#1335
1#
#1340
b01101011 "
0#
b0000000001000000 %
b10000100 &
b1110 (
#1345
1#
#1350
b10010001 !
b01101010 "
0#
b0000000010000000 %
b10000101 &
b1100 (
#1355
1#
#1360
b10001110 !
b01101001 "
0#
b0000000100000000 %
b10000110 &
b1000 (
#1365
1#
#1370
b10001000 !
b01101000 "
0#
b0000001000000000 %
b10000111 &
b0001 (
#1375
1#
#1380
b10001010 !
b01100111 "
0#
b0000010000000000 %
b10001000 &
b0010 (
1)
#1385
1#
#1390
b10001101 !
b11110001 "
0#
b0000100000000000 %
b10001001 &
b0100 (
#1395
1#
#1400
b10010011 !
b01111110 "
0#
b0001000000000000 %
b10001010 &
b1001 (
#1405
1#
#1410
b10001110 !
b00010001 "
0#
b0010000000000000 %
b10001011 &
b0011 (
#1415
1#
#1420
b10010010 !
b10011111 "
0#
b0100000000000001 %
b10001100 &
b0110 (
#1425
1#
#1430
b10011010 !
b00110001 "
0#
b1000000000000010 %
b10001101 &
b1101 (
#1435
1#
#1440
b10011000 !
b11001011 "
0#
b0000000000000101 %
b10001110 &
b1010 (
#1445
1#
#1450
b10010100 !
b01100011 "
0#
b0000000000001010 %
b10001111 &
b0101 (
#1455
1#
#1460
b10011011 !
b11110111 "
0#
b0000000000010100 %
b10010000 &
b1011 (
0)
#1465
1#
#1470
b10011000 !
b11110110 "
0#
b0000000000101000 %
b10010001 &
b0111 (
#1475
1#
#1480
b10100001 !
b11110101 "
0#
b0000000001010000 %
b10010010 &
b1111 (
#1485
1#
#1490
b11110100 "
0#
b0000000010100000 %
b10010011 &
b1110 (
#1495
1#
#1500
b10100000 !
b11110011 "
0#
b0000000101000000 %
b10010100 &
b1100 (
#1505
1#
#1510
b10011101 !
b11110010 "
0#
b0000001010000000 %
b10010101 &
b1000 (
#1515
1#
#1520
b10010111 !
b11110001 "
0#
b0000010100000000 %
b10010110 &
b0001 (
#1525
1#
#1530
b10011001 !
b11110000 "
0#
b0000101000000000 %
b10010111 &
b0010 (
#1535
1#
#1540
b10011100 !
b11101111 "
0#
b0001010000000000 %
b10011000 &
b0100 (
1)
#1545
1#
#1550
b10100010 !
b10001011 "
0#
b0010100000000000 %
b10011001 &
b1001 (
#1555
1#
#1560
b10011101 !
b00101101 "
0#
b0101000000000001 %
b10011010 &
b0011 (
#1565
1#
#1570
b10100001 !
b11001010 "
0#
b1010000000000010 %
b10011011 &
b0110 (
#1575
1#
#1580
b10101001 !
b01101011 "
0#
b0100000000000100 %
b10011100 &
b1101 (
#1585
1#
#1590
b10100111 !
b00010100 "
0#
b1000000000001000 %
b10011101 &
b1010 (
#1595
1#
#1600
b10100011 !
b10111011 "
0#
b0000000000010001 %
b10011110 &
b0101 (
#1605
1#
#1610
b10101010 !
b01011110 "
0#
b0000000000100010 %
b10011111 &
b1011 (
#1615
1#
#1620
b10100111 !
b00001000 "
0#
b0000000001000100 %
b10100000 &
b0111 (
0)
#1625
1#
#1630
b10110000 !
b00000111 "
0#
b0000000010001000 %
b10100001 &
b1111 (
#1635
1#
#1640
b00000110 "
0#
b0000000100010000 %
b10100010 &
b1110 (
#1645
1#
#1650
b10101111 !
b00000101 "
0#
b0000001000100000 %
b10100011 &
b1100 (
#1655
1#
#1660
b10101100 !
b00000100 "
0#
b0000010001000000 %
b10100100 &
b1000 (
#1665
1#
#1670
b10100110 !
b00000011 "
0#
b0000100010000000 %
b10100101 &
b0001 (
#1675
1#
#1680
b10101000 !
b00000010 "
0#
b0001000100000000 %
b10100110 &
b0010 (
#1685
1#
#1690
b10101011 !
b00000001 "
0#
b0010001000000000 %
b10100111 &
b0100 (
#1695
1#
#1700
b10110001 !
b00000000 "
0#
b0100010000000001 %
b10101000 &
b1001 (
1)
#1705
1#
#1710
b10101100 !
b10110001 "
0#
b1000100000000010 %
b10101001 &
b0011 (
#1715
1#
#1720
b10110000 !
b01011101 "
0#
b0001000000000101 %
b10101010 &
b0110 (
#1725
1#
#1730
b10111000 !
b00001101 "
0#
b0010000000001010 %
b10101011 &
b1101 (
#1735
1#
#1740
b10110110 !
b11000101 "
0#
b0100000000010101 %
b10101100 &
b1010 (
#1745
1#
#1750
b10110010 !
b01111011 "
0#
b1000000000101010 %
b10101101 &
b0101 (
#1755
1#
#1760
b10111001 !
b00101101 "
0#
b0000000001010101 %
b10101110 &
b1011 (
#1765
1#
#1770
b10110110 !
b11100110 "
0#
b0000000010101010 %
b10101111 &
b0111 (
#1775
1#
#1780
b10111111 !
b10011100 "
0#
b0000000101010100 %
b10110000 &
b1111 (
0)
#1785
1#
#1790
b10011011 "
0#
b0000001010101000 %
b10110001 &
b1110 (
#1795
1#
#1800
b10111110 !
b10011010 "
0#
b0000010101010000 %
b10110010 &
b1100 (
#1805
1#
#1810
b10111011 !
b10011001 "
0#
b0000101010100000 %
b10110011 &
b1000 (
#1815
1#
#1820
b10110101 !
b10011000 "
0#
b0001010101000000 %
b10110100 &
b0001 (
#1825
1#
#1830
b10110111 !
b10010111 "
0#
b0010101010000000 %
b10110101 &
b0010 (
#1835
1#
#1840
b10111010 !
b10010110 "
0#
b0101010100000001 %
b10110110 &
b0100 (
#1845
1#
#1850
b11000000 !
b10010101 "
0#
b1010101000000010 %
b10110111 &
b1001 (
#1855
1#
#1860
b10111011 !
b10010100 "
0#
b0101010000000100 %
b10111000 &
b0011 (
1)
#1865
1#
#1870
b10111111 !
b01001111 "
0#
b1010100000001000 %
b10111001 &
b0110 (
#1875
1#
#1880
b11000111 !
b00001110 "
0#
b0101000000010000 %
b10111010 &
b1101 (
#1885
1#
#1890
b11000101 !
b11010101 "
0#
b1010000000100000 %
b10111011 &
b1010 (
#1895
1#
#1900
b11000001 !
b10011010 "
0#
b0100000001000000 %
b10111100 &
b0101 (
#1905
1#
#1910
b11001000 !
b01011011 "
0#
b1000000010000000 %
b10111101 &
b1011 (
#1915
1#
#1920
b11000101 !
b00100011 "
0#
b0000000100000001 %
b10111110 &
b0111 (
#1925
1#
#1930
b11001110 !
b11101000 "
0#
b0000001000000010 %
b10111111 &
1'
b1111 (
#1935
1#
#1940
b10110110 "
0#
b0000010000000100 %
b11000000 &
0'
b1110 (
0)
#1945
1#
#1950
b11001101 !
b10110101 "
0#
b0000100000001000 %
b11000001 &
b1100 (
#1955
1#
#1960
b11001010 !
b10110100 "
0#
b0001000000010000 %
b11000010 &
b1000 (
#1965
1#
#1970
b11000100 !
b10110011 "
0#
b0010000000100000 %
b11000011 &
b0001 (
#1975
1#
#1980
b11000110 !
b10110010 "
0#
b0100000001000001 %
b11000100 &
b0010 (
#1985
1#
#1990
b11001001 !
b10110001 "
0#
b1000000010000010 %
b11000101 &
b0100 (
#1995
1#
#2000
b11001111 !
b10110000 "
0#
b0000000100000101 %
b11000110 &
b1001 (
#2005
1#
#2010
b11001010 !
b10101111 "
0#
b0000001000001010 %
b11000111 &
b0011 (
#2015
1#
#2020
b11001110 !
b10101110 "
0#
b0000010000010100 %
b11001000 &
b0110 (
1)
#2025
1#
#2030
b11010110 !
b01111100 "
0#
b0000100000101000 %
b11001001 &
b1101 (
#2035
1#
#2040
b11010100 !
b01010010 "
0#
b0001000001010000 %
b11001010 &
b1010 (
#2045
1#
#2050
b11010000 !
b00100110 "
0#
b0010000010100000 %
b11001011 &
b0101 (
#2055
1#
#2060
b11010111 !
b11110110 "
0#
b0100000101000001 %
b11001100 &
b1011 (
#2065
1#
#2070
b11010100 !
b11001101 "
0#
b1000001010000010 %
b11001101 &
b0111 (
#2075
1#
#2080
b11011101 !
b10100001 "
0#
b0000010100000101 %
b11001110 &
b1111 (
#2085
1#
#2090
b01111110 "
0#
b0000101000001010 %
b11001111 &
b1110 (
#2095
1#
#2100
b11011100 !
b01011011 "
0#
b0001010000010100 %
b11010000 &
b1100 (
0)
#2105
1#
#2110
b11011001 !
b01011010 "
0#
b0010100000101000 %
b11010001 &
b1000 (
#2115
1#
#2120
b11010011 !
b01011001 "
0#
b0101000001010001 %
b11010010 &
b0001 (
#2125
1#
#2130
b11010101 !
b01011000 "
0#
b1010000010100010 %
b11010011 &
b0010 (
#2135
1#
#2140
b11011000 !
b01010111 "
0#
b0100000101000100 %
b11010100 &
b0100 (
#2145
1#
#2150
b11011110 !
b01010110 "
0#
b1000001010001000 %
b11010101 &
b1001 (
#2155
1#
#2160
b11011001 !
b01010101 "
0#
b0000010100010001 %
b11010110 &
b0011 (
#2165
1#
#2170
b11011101 !
b01010100 "
0#
b0000101000100010 %
b11010111 &
b0110 (
#2175
1#
#2180
b11100101 !
b01010011 "
0#
b0001010001000100 %
b11011000 &
b1101 (
1)
#2185
1#
#2190
b11100011 !
b00111000 "
0#
b0010100010001000 %
b11011001 &
b1010 (
#2195
1#
#2200
b11011111 !
b00011011 "
0#
b0101000100010001 %
b11011010 &
b0101 (
#2205
1#
#2210
b11100110 !
b11111010 "
0#
b1010001000100010 %
b11011011 &
b1011 (
#2215
1#
#2220
b11100011 !
b11100000 "
0#
b0100010001000100 %
b11011100 &
b0111 (
#2225
1#
#2230
b11101100 !
b11000011 "
0#
b1000100010001000 %
b11011101 &
b1111 (
#2235
1#
#2240
b10101111 "
0#
b0001000100010001 %
b11011110 &
b1110 (
#2245
1#
#2250
b11101011 !
b10011011 "
0#
b0010001000100010 %
b11011111 &
b1100 (
#2255
1#
#2260
b11101000 !
b10000110 "
0#
b0100010001000101 %
b11100000 &
b1000 (
0)
#2265
1#
#2270
b11100010 !
b10000101 "
0#
b1000100010001010 %
b11100001 &
b0001 (
#2275
1#
#2280
b11100100 !
b10000100 "
0#
b0001000100010101 %
b11100010 &
b0010 (
#2285
1#
#2290
b11100111 !
b10000011 "
0#
b0010001000101010 %
b11100011 &
b0100 (
#2295
1#
#2300
b11101101 !
b10000010 "
0#
b0100010001010101 %
b11100100 &
b1001 (
#2305
1#
#2310
b11101000 !
b10000001 "
0#
b1000100010101010 %
b11100101 &
b0011 (
#2315
1#
#2320
b11101100 !
b10000000 "
0#
b0001000101010101 %
b11100110 &
b0110 (
#2325
1#
#2330
b11110100 !
b01111111 "
0#
b0010001010101010 %
b11100111 &
b1101 (
#2335
1#
#2340
b11110010 !
b01111110 "
0#
b0100010101010101 %
b11101000 &
b1010 (
1)
#2345
1#
#2350
b11101110 !
b01110000 "
0#
b1000101010101010 %
b11101001 &
b0101 (
#2355
1#
#2360
b11110101 !
b01011110 "
0#
b0001010101010101 %
b11101010 &
b1011 (
#2365
1#
#2370
b11110010 !
b01010011 "
0#
b0010101010101010 %
b11101011 &
b0111 (
#2375
1#
#2380
b11111011 !
b01000101 "
0#
b0101010101010101 %
b11101100 &
b1111 (
#2385
1#
#2390
b01000000 "
0#
b1010101010101010 %
b11101101 &
b1110 (
#2395
1#
#2400
b11111010 !
b00111011 "
0#
b0101010101010100 %
b11101110 &
b1100 (
#2405
1#
#2410
b11110111 !
b00110101 "
0#
b1010101010101000 %
b11101111 &
b1000 (
#2415
1#
#2420
b11110001 !
b00101100 "
0#
b0101010101010000 %
b11110000 &
b0001 (
0)
#2425
1#
#2430
b11110011 !
b00101011 "
0#
b1010101010100000 %
b11110001 &
b0010 (
#2435
1#
#2440
b11110110 !
b00101010 "
0#
b0101010101000000 %
b11110010 &
b0100 (
#2445
1#
#2450
b11111100 !
b00101001 "
0#
b1010101010000000 %
b11110011 &
b1001 (
#2455
1#
#2460
b11110111 !
b00101000 "
0#
b0101010100000000 %
b11110100 &
b0011 (
#2465
1#
#2470
b11111011 !
b00100111 "
0#
b1010101000000000 %
b11110101 &
b0110 (
#2475
1#
#2480
b00000011 !
b00100110 "
0#
b0101010000000000 %
b11110110 &
b1101 (
#2485
1#
#2490
b00000001 !
b00100101 "
0#
b1010100000000000 %
b11110111 &
b1010 (
#2495
1#
#2500
b11111101 !
b00100100 "
0#
b0101000000000000 %
b11111000 &
b0101 (
1)
#2505
1#
#2510
b00000100 !
b00100001 "
0#
b1010000000000000 %
b11111001 &
b1011 (
#2515
1#
#2520
b00000001 !
b00100101 "
0#
b0100000000000000 %
b11111010 &
b0111 (
#2525
1#
#2530
b00001010 !
b00100110 "
0#
b1000000000000000 %
b11111011 &
b1111 (
#2535
1#
#2540
b00110000 "
0#
b0000000000000001 %
b11111100 &
b1110 (
#2545
1#
#2550
b00001001 !
b00111010 "
0#
b0000000000000010 %
b11111101 &
b1100 (
#2555
1#
#2560
b00000110 !
b01000011 "
0#
b0000000000000100 %
b11111110 &
b1000 (
#2565
1#
#2570
b00000000 !
b01001001 "
0#
b0000000000001000 %
b11111111 &
1'
b0001 (
#2575
1#
#2580
b00000010 !
0#
b0000000000010000 %
b00000000 &
0'
b0010 (
0)
#2585
1#
#2590
b00000101 !
b01001000 "
0#
b0000000000100000 %
b00000001 &
b0100 (
#2595
1#
#2600
b00001011 !
b01000111 "
0#
b0000000001000000 %
b00000010 &
b1001 (
#2605
1#
#2610
b00000110 !
b01000110 "
0#
b0000000010000000 %
b00000011 &
b0011 (
#2615
1#
#2620
b00001010 !
b01000101 "
0#
b0000000100000000 %
b00000100 &
b0110 (
#2625
1#
#2630
b00010010 !
b01000100 "
0#
b0000001000000000 %
b00000101 &
b1101 (
#2635
1#
#2640
b00010000 !
b01000011 "
0#
b0000010000000000 %
b00000110 &
b1010 (
#2645
1#
#2650
b00001100 !
b01000010 "
0#
b0000100000000000 %
b00000111 &
b0101 (
#2655
1#
#2660
b00010011 !
b01000001 "
0#
b0001000000000000 %
b00001000 &
b1011 (
1)
#2665
1#
#2670
b00010000 !
b01010100 "
0#
b0010000000000000 %
b00001001 &
b0111 (
#2675
1#
#2680
b00011001 !
b01100100 "
0#
b0100000000000001 %
b00001010 &
b1111 (
#2685
1#
#2690
b01111101 "
0#
b1000000000000010 %
b00001011 &
b1110 (
#2695
1#
#2700
b00011000 !
b10010110 "
0#
b0000000000000101 %
b00001100 &
b1100 (
#2705
1#
#2710
b00010101 !
b10101110 "
0#
b0000000000001010 %
b00001101 &
b1000 (
#2715
1#
#2720
b00001111 !
b11000011 "
0#
b0000000000010100 %
b00001110 &
b0001 (
#2725
1#
#2730
b00010001 !
b11010010 "
0#
b0000000000101000 %
b00001111 &
b0010 (
#2735
1#
#2740
b00010100 !
b11100011 "
0#
b0000000001010000 %
b00010000 &
b0100 (
0)
#2745
1#
#2750
b00011010 !
b11100010 "
0#
b0000000010100000 %
b00010001 &
b1001 (
#2755
1#
#2760
b00010101 !
b11100001 "
0#
b0000000101000000 %
b00010010 &
b0011 (
#2765
1#
#2770
b00011001 !
b11100000 "
0#
b0000001010000000 %
b00010011 &
b0110 (
#2775
1#
#2780
b00100001 !
b11011111 "
0#
b0000010100000000 %
b00010100 &
b1101 (
#2785
1#
